{
  "project_info": {
    "project_number": "376524898273",
    "project_id": "news-app-617b0",
    "storage_bucket": "news-app-617b0.appspot.com"
  },
  "client": [
    {
      "client_info": {
        "mobilesdk_app_id": "1:376524898273:android:824dee57f39588cb011ca0",
        "android_client_info": {
          "package_name": "com.example.newsapp"
        }
      },
      "oauth_client": [
        {
          "client_id": "376524898273-a5trbmc7fi2ft03ai41c9egb5hp7rq69.apps.googleusercontent.com",
          "client_type": 3
        }
      ],
      "api_key": [
        {
          "current_key": "AIzaSyAIK83ps5RXG5jFAfv-FaN-T4_-e2plqf0"
        }
      ],
      "services": {
        "appinvite_service": {
          "other_platform_oauth_client": [
            {
              "client_id": "376524898273-a5trbmc7fi2ft03ai41c9egb5hp7rq69.apps.googleusercontent.com",
              "client_type": 3
            }
          ]
        }
      }
    }
  ],
  "configuration_version": "1"
}